oimodeler/__init__.py
oimodeler/oimBasicFourierComponents.py
oimodeler/oimComponent.py
oimodeler/oimData.py
oimodeler/oimDataFilter.py
oimodeler/oimFTBackends.py
oimodeler/oimFitter.py
oimodeler/oimFluxData.py
oimodeler/oimModel.py
oimodeler/oimOptions.py
oimodeler/oimParam.py
oimodeler/oimPlots.py
oimodeler/oimSimulator.py
oimodeler/oimUtils.py
oimodeler/oimCustomComponents/__init__.py
oimodeler/oimCustomComponents/oimBox.py
oimodeler/oimCustomComponents/oimExpRing.py
oimodeler/oimCustomComponents/oimFastRotator.py
oimodeler/oimCustomComponents/oimKinematicDisk.py
oimodeler/oimCustomComponents/oimSpiral.py
oimodeler/tests/conftest.py
oimodeler/tests/test_io.py
oimodeler/tests/test_oimModel.py
oimodeler-0.8.1.dist-info/LICENSE
oimodeler-0.8.1.dist-info/METADATA
oimodeler-0.8.1.dist-info/WHEEL
oimodeler-0.8.1.dist-info/top_level.txt
oimodeler-0.8.1.dist-info/RECORD
