Metadata-Version: 2.1
Name: oimodeler
Version: 0.8.1
Summary: Optical interferometry modelling tool
Author-email: Anthony meilland <ame@oca.eu>
License: GPLv3
Project-URL: Github, https://gitlab.oca.eu/oimodeler/oimodeler
Keywords: optical,interferometry,modeling
Classifier: Development Status :: 3 - Alpha
Classifier: Intended Audience :: Science/Research
Classifier: License :: OSI Approved :: GNU General Public License v3 (GPLv3)
Classifier: Operating System :: MacOS :: MacOS X
Classifier: Operating System :: POSIX :: AIX
Classifier: Operating System :: POSIX :: Linux
Classifier: Programming Language :: Python :: 3
Classifier: Programming Language :: Python :: 3.8
Classifier: Programming Language :: Python :: 3.9
Classifier: Programming Language :: Python :: 3.10
Classifier: Programming Language :: Python :: 3 :: Only
Classifier: Topic :: Scientific/Engineering :: Astronomy
Classifier: Natural Language :: English
Classifier: Typing :: Typed
Requires-Python: >=3.8
License-File: LICENSE
Requires-Dist: astropy (>=5.2.1)
Requires-Dist: astroquery (>=0.4.6)
Requires-Dist: corner (>=2.2.1)
Requires-Dist: emcee (>=3.1.4)
Requires-Dist: matplotlib (>=3.6.3)
Requires-Dist: numpy (>=1.24.1)
Requires-Dist: scipy (>=1.10.0)
Requires-Dist: tqdm (>=4.64.1)
